Datagrade
