Metadata-Version: 2.1
Name: Datagrade
Version: 1.0.8
Summary: Datascience library
Home-page: https://github.com/GoosenLilac/datagrade
Author: Guseyn Isma
Author-email: rms_gen@mail.ru
License: Apache-2.0
Platform: UNKNOWN
License-File: LICENSE.txt
